kaizen/__init__.py
kaizen/actors/__init__.py
kaizen/actors/api_test_runner.py
kaizen/actors/e2e_test_runner.py
kaizen/actors/unit_test_runner.py
kaizen/formatters/code_review_formatter.py
kaizen/generator/__init__.py
kaizen/generator/api_test.py
kaizen/generator/code_fixer.py
kaizen/generator/e2e_tests.py
kaizen/generator/issue_analysis.py
kaizen/generator/pr_description.py
kaizen/generator/unit_test.py
kaizen/helpers/__init__.py
kaizen/helpers/general.py
kaizen/helpers/output.py
kaizen/helpers/parser.py
kaizen/helpers/patterns.py
kaizen/integrations/__init__.py
kaizen/llms/__init__.py
kaizen/llms/prompts/API_tests_prompts.py
kaizen/llms/prompts/ask_question_prompts.py
kaizen/llms/prompts/code_fix_prompts.py
kaizen/llms/prompts/code_review_prompts.py
kaizen/llms/prompts/code_scan_prompts.py
kaizen/llms/prompts/e2e_tests_prompts.py
kaizen/llms/prompts/general_prompts.py
kaizen/llms/prompts/issue_analysis_prompts.py
kaizen/llms/prompts/pr_desc_prompts.py
kaizen/llms/prompts/ui_reviewer_prompts.py
kaizen/llms/prompts/unit_tests_prompts.py
kaizen/llms/prompts/work_summary_prompts.py
kaizen/llms/provider.py
kaizen/parsers/__init__.py
kaizen/parsers/javascriptparser.py
kaizen/parsers/pythonparser.py
kaizen/parsers/reactparser.py
kaizen/parsers/reacttsparser.py
kaizen/parsers/rustparser.py
kaizen/parsers/typescriptparser.py
kaizen/reviewer/__init__.py
kaizen/reviewer/ask_question.py
kaizen/reviewer/code_review.py
kaizen/reviewer/code_scan.py
kaizen/reviewer/ui_review.py
kaizen/reviewer/work_summarizer.py
kaizen/tests/__init__.py
kaizen/tests/actions/diff_pr_test.py
kaizen/tests/actions/test_review.py
kaizen/tests/data/actions/valid_review.json
kaizen/tests/helpers/test_diff_to_numbered_lines.py
kaizen/tests/helpers/test_output.py
kaizen/tests/helpers/test_patch_parser.py
kaizen/tests/llms/test_provider.py
kaizen/utils/__init__.py
kaizen/utils/config.py
kaizen/visualizer/__init__.py
kaizen/visualizer/code_visualizer.py
kaizen_cloudcode-0.4.21.dist-info/LICENSE
kaizen_cloudcode-0.4.21.dist-info/METADATA
kaizen_cloudcode-0.4.21.dist-info/WHEEL
kaizen_cloudcode-0.4.21.dist-info/RECORD
