Metadata-Version: 2.1
Name: kaizen-cloudcode
Version: 0.4.21
Summary: An intelligent coding companion that accelerates your development workflow by providing efficient assistance, enabling you to craft high-quality code more rapidly.
License: Apache2.0
Author: Saurav Panda
Author-email: saurav.panda@cloudcode.ai
Requires-Python: >=3.9.0,<4.0.0
Classifier: License :: Other/Proprietary License
Classifier: Programming Language :: Python :: 3
Classifier: Programming Language :: Python :: 3.9
Classifier: Programming Language :: Python :: 3.10
Classifier: Programming Language :: Python :: 3.11
Classifier: Programming Language :: Python :: 3.12
Classifier: Programming Language :: Python :: 3.13
Provides-Extra: all
Provides-Extra: javascript
Provides-Extra: python
Provides-Extra: rust
Provides-Extra: typescript
Requires-Dist: black (>=24.3.0,<25.0.0)
Requires-Dist: boto3 (>=1.35.5,<2.0.0)
Requires-Dist: bs4 (>=0.0.2,<0.0.3)
Requires-Dist: cryptography (>=42.0.5,<44.0.0)
Requires-Dist: escodegen (>=1.0.11,<2.0.0)
Requires-Dist: esprima (>=4.0.1,<5.0.0)
Requires-Dist: fastapi (>=0.115.2,<0.116.0)
Requires-Dist: flake8 (>=7.0.0,<8.0.0)
Requires-Dist: fuzzywuzzy (>=0.18.0,<0.19.0)
Requires-Dist: gitpython (>=3.1.43,<4.0.0)
Requires-Dist: litellm (>=1.40.29,<2.0.0)
Requires-Dist: llama-index (>=0.10.65,<0.11.0)
Requires-Dist: llama-index-core (==0.10.65)
Requires-Dist: llama-index-embeddings-litellm (>=0.1.1,<0.2.0)
Requires-Dist: llama-index-llms-litellm (>=0.1.4,<0.2.0)
Requires-Dist: llama-index-readers-file (>=0.1.25,<0.2.0)
Requires-Dist: nest-asyncio (>=1.6.0,<2.0.0)
Requires-Dist: pip (>=24.0,<25.0)
Requires-Dist: pre-commit (>=3.8.0,<4.0.0)
Requires-Dist: psycopg2-binary (>=2.9.9,<3.0.0)
Requires-Dist: pygithub (>=2.4.0,<3.0.0)
Requires-Dist: pyjwt (>=2.8.0,<3.0.0)
Requires-Dist: pytest-playwright (>=0.4.4,<0.5.0)
Requires-Dist: python-levenshtein (>=0.25.1,<0.26.0)
Requires-Dist: qdrant-client (>=1.11.0,<2.0.0)
Requires-Dist: redis (>=5.0.7,<6.0.0)
Requires-Dist: requests (>=2.31.0,<3.0.0)
Requires-Dist: ruff (>=0.6.5,<0.7.0)
Requires-Dist: sqlalchemy (>=2.0.31,<3.0.0)
Requires-Dist: starlette (==0.40.0)
Requires-Dist: tqdm (>=4.66.5,<5.0.0)
Requires-Dist: tree-sitter (>=0.23.0,<0.24.0)
Requires-Dist: tree-sitter-javascript (>=0.23.0,<0.24.0) ; extra == "javascript" or extra == "all"
Requires-Dist: tree-sitter-python (==0.23.2) ; extra == "python" or extra == "all"
Requires-Dist: tree-sitter-rust (>=0.23.0,<0.24.0) ; extra == "rust" or extra == "all"
Requires-Dist: tree-sitter-typescript (>=0.23.0,<0.24.0) ; extra == "typescript" or extra == "all"
Requires-Dist: uvicorn (>=0.29.0,<0.30.0)
